{
    "best_params": {
        "reset_peak": false,
        "rsi_min_thresh": 43,
        "rsi_max_thresh": 50,
        "adx_thresh": 54.53836982324864,
        "atr_mult": 17.19124436281302,
        "vwap_atr_mult": 0.8557727003515059,
        "buy_factor": 0.7340902622768063,
        "sell_factor": 0.037656920188872296,
        "trailstop_pct": 15.511181451431836,
        "sign_thresh_pair": "ema_3|ema_8"
    },
    "best_value": 90.56564799999998,
    "importances": {
        "atr_mult": 0.35177543288463375,
        "adx_thresh": 0.3312446987435912,
        "sell_factor": 0.13521234473832858,
        "buy_factor": 0.07946787842501557,
        "trailstop_pct": 0.049975275864734985,
        "rsi_min_thresh": 0.03702485311793157,
        "vwap_atr_mult": 0.015299516225764417,
        "sign_thresh_pair": 0.0,
        "reset_peak": 0.0
    },
    "trials": [
        {
            "number": 0,
            "value": 19.798213333333344,
            "params": {
                "reset_peak": false,
                "rsi_min_thresh": 40,
                "rsi_max_thresh": 60,
                "adx_thresh": 50.92870188622365,
                "atr_mult": 15.898726899684341,
                "vwap_atr_mult": 1.2775771490233265,
                "buy_factor": 0.6080344351768159,
                "sell_factor": 0.05763069730785687,
                "trailstop_pct": 17.809182758886628,
                "sign_thresh_pair": "ema_3|ema_8"
            },
            "state": "COMPLETE"
        },
        {
            "number": 1,
            "value": 1.0647946666666637,
            "params": {
                "reset_peak": false,
                "rsi_min_thresh": 41,
                "rsi_max_thresh": 64,
                "adx_thresh": 50.08551854844892,
                "atr_mult": 10.811774432296147,
                "vwap_atr_mult": 1.964889238142412,
                "buy_factor": 0.4746505827293909,
                "sell_factor": 0.018807761240503637,
                "trailstop_pct": 25.549971243967597,
                "sign_thresh_pair": "ema_3|ema_8"
            },
            "state": "COMPLETE"
        },
        {
            "number": 2,
            "value": 37.520346666666654,
            "params": {
                "reset_peak": false,
                "rsi_min_thresh": 25,
                "rsi_max_thresh": 58,
                "adx_thresh": 57.15766906541094,
                "atr_mult": 16.357923313630316,
                "vwap_atr_mult": 2.928970185692608,
                "buy_factor": 0.7988562397871303,
                "sell_factor": 0.09711093556800954,
                "trailstop_pct": 23.291745276173287,
                "sign_thresh_pair": "ema_3|ema_8"
            },
            "state": "COMPLETE"
        },
        {
            "number": 3,
            "value": 20.407535999999972,
            "params": {
                "reset_peak": false,
                "rsi_min_thresh": 34,
                "rsi_max_thresh": 63,
                "adx_thresh": 57.355368794635645,
                "atr_mult": 14.610102913710465,
                "vwap_atr_mult": 1.893929294796484,
                "buy_factor": 0.5277921607707963,
                "sell_factor": 0.09701587564552162,
                "trailstop_pct": 16.463661098741387,
                "sign_thresh_pair": "ema_3|ema_8"
            },
            "state": "COMPLETE"
        },
        {
            "number": 4,
            "value": 41.12290666666666,
            "params": {
                "reset_peak": false,
                "rsi_min_thresh": 40,
                "rsi_max_thresh": 62,
                "adx_thresh": 54.3649490538317,
                "atr_mult": 15.764872734376851,
                "vwap_atr_mult": 0.9841877153365544,
                "buy_factor": 0.5769147583476302,
                "sell_factor": 0.056249794336260775,
                "trailstop_pct": 18.931565882035287,
                "sign_thresh_pair": "ema_3|ema_8"
            },
            "state": "COMPLETE"
        },
        {
            "number": 5,
            "value": 19.276261333333327,
            "params": {
                "reset_peak": false,
                "rsi_min_thresh": 42,
                "rsi_max_thresh": 52,
                "adx_thresh": 53.144659569928024,
                "atr_mult": 11.36232593631344,
                "vwap_atr_mult": 1.3074613222573253,
                "buy_factor": 0.6044603739779636,
                "sell_factor": 0.05790957192208854,
                "trailstop_pct": 16.872644554100052,
                "sign_thresh_pair": "ema_3|ema_8"
            },
            "state": "COMPLETE"
        },
        {
            "number": 6,
            "value": 28.423685333333314,
            "params": {
                "reset_peak": false,
                "rsi_min_thresh": 34,
                "rsi_max_thresh": 64,
                "adx_thresh": 51.95335618965332,
                "atr_mult": 14.382700692333502,
                "vwap_atr_mult": 1.9312118295671126,
                "buy_factor": 0.764289846703214,
                "sell_factor": 0.056131326731851394,
                "trailstop_pct": 19.14751673464084,
                "sign_thresh_pair": "ema_3|ema_8"
            },
            "state": "COMPLETE"
        },
        {
            "number": 7,
            "value": 29.088522666666666,
            "params": {
                "reset_peak": false,
                "rsi_min_thresh": 41,
                "rsi_max_thresh": 61,
                "adx_thresh": 53.18290245696954,
                "atr_mult": 14.384907145068764,
                "vwap_atr_mult": -0.7883863262760369,
                "buy_factor": 0.6335830727580021,
                "sell_factor": 0.06962124283451508,
                "trailstop_pct": 24.190663635928225,
                "sign_thresh_pair": "ema_3|ema_8"
            },
            "state": "COMPLETE"
        },
        {
            "number": 8,
            "value": 20.036898666666662,
            "params": {
                "reset_peak": false,
                "rsi_min_thresh": 33,
                "rsi_max_thresh": 45,
                "adx_thresh": 53.298635182248724,
                "atr_mult": 15.63617945119886,
                "vwap_atr_mult": 2.167638798365592,
                "buy_factor": 0.7528122996645911,
                "sell_factor": 0.08670619572587487,
                "trailstop_pct": 19.292180417824806,
                "sign_thresh_pair": "ema_3|ema_8"
            },
            "state": "COMPLETE"
        },
        {
            "number": 9,
            "value": 2.415839999999987,
            "params": {
                "reset_peak": false,
                "rsi_min_thresh": 37,
                "rsi_max_thresh": 57,
                "adx_thresh": 51.052480422239114,
                "atr_mult": 15.945356724324547,
                "vwap_atr_mult": 1.4676204759441882,
                "buy_factor": 0.6635013000543396,
                "sell_factor": 0.05677960541760556,
                "trailstop_pct": 17.910322299462674,
                "sign_thresh_pair": "ema_3|ema_8"
            },
            "state": "COMPLETE"
        },
        {
            "number": 10,
            "value": 2.2427093333333494,
            "params": {
                "reset_peak": false,
                "rsi_min_thresh": 28,
                "rsi_max_thresh": 53,
                "adx_thresh": 59.57519402582452,
                "atr_mult": 17.365620077118088,
                "vwap_atr_mult": -0.036735211971001824,
                "buy_factor": 0.4259188563556264,
                "sell_factor": 0.027669045691240075,
                "trailstop_pct": 11.173731427712204,
                "sign_thresh_pair": "ema_3|ema_8"
            },
            "state": "COMPLETE"
        },
        {
            "number": 11,
            "value": 49.750562666666646,
            "params": {
                "reset_peak": false,
                "rsi_min_thresh": 25,
                "rsi_max_thresh": 57,
                "adx_thresh": 55.914369683701054,
                "atr_mult": 17.903679324108747,
                "vwap_atr_mult": 0.6167725657756215,
                "buy_factor": 0.6956990882324599,
                "sell_factor": 0.0335663880420316,
                "trailstop_pct": 29.515117938823018,
                "sign_thresh_pair": "ema_3|ema_8"
            },
            "state": "COMPLETE"
        },
        {
            "number": 12,
            "value": 68.75295733333327,
            "params": {
                "reset_peak": false,
                "rsi_min_thresh": 45,
                "rsi_max_thresh": 53,
                "adx_thresh": 55.49931083715316,
                "atr_mult": 17.74499055258929,
                "vwap_atr_mult": 0.36997704787956087,
                "buy_factor": 0.6966633163406795,
                "sell_factor": 0.034200582360343054,
                "trailstop_pct": 29.896659654903786,
                "sign_thresh_pair": "ema_3|ema_8"
            },
            "state": "COMPLETE"
        },
        {
            "number": 13,
            "value": 40.591861333333334,
            "params": {
                "reset_peak": false,
                "rsi_min_thresh": 29,
                "rsi_max_thresh": 49,
                "adx_thresh": 57.07775770345493,
                "atr_mult": 12.534324084672338,
                "vwap_atr_mult": 0.46949042056087836,
                "buy_factor": 0.689599059113805,
                "sell_factor": 0.03440197878423703,
                "trailstop_pct": 29.638577691479647,
                "sign_thresh_pair": "ema_3|ema_8"
            },
            "state": "COMPLETE"
        },
        {
            "number": 14,
            "value": 58.59572799999999,
            "params": {
                "reset_peak": false,
                "rsi_min_thresh": 45,
                "rsi_max_thresh": 54,
                "adx_thresh": 55.846624912662236,
                "atr_mult": 17.727447922727166,
                "vwap_atr_mult": -0.07190797166380858,
                "buy_factor": 0.7067461645445977,
                "sell_factor": 0.03675752395764944,
                "trailstop_pct": 29.857966261117802,
                "sign_thresh_pair": "ema_3|ema_8"
            },
            "state": "COMPLETE"
        },
        {
            "number": 15,
            "value": 43.49278933333333,
            "params": {
                "reset_peak": false,
                "rsi_min_thresh": 45,
                "rsi_max_thresh": 53,
                "adx_thresh": 55.65495762251358,
                "atr_mult": 12.91067958107193,
                "vwap_atr_mult": -0.3699742974123841,
                "buy_factor": 0.7230095948243364,
                "sell_factor": 0.041008134410943885,
                "trailstop_pct": 27.554731529249477,
                "sign_thresh_pair": "ema_3|ema_8"
            },
            "state": "COMPLETE"
        },
        {
            "number": 16,
            "value": 4.821237333333338,
            "params": {
                "reset_peak": false,
                "rsi_min_thresh": 45,
                "rsi_max_thresh": 50,
                "adx_thresh": 59.07584040127472,
                "atr_mult": 17.262234645829032,
                "vwap_atr_mult": 0.047068907876277155,
                "buy_factor": 0.5450393709837437,
                "sell_factor": 0.019623836802605935,
                "trailstop_pct": 26.247795079726245,
                "sign_thresh_pair": "ema_3|ema_8"
            },
            "state": "COMPLETE"
        },
        {
            "number": 17,
            "value": 59.371888000000006,
            "params": {
                "reset_peak": false,
                "rsi_min_thresh": 37,
                "rsi_max_thresh": 55,
                "adx_thresh": 54.55875936853392,
                "atr_mult": 17.847818974929496,
                "vwap_atr_mult": -0.910276321162669,
                "buy_factor": 0.6543538100730406,
                "sell_factor": 0.04353475569926346,
                "trailstop_pct": 21.81400159646075,
                "sign_thresh_pair": "ema_3|ema_8"
            },
            "state": "COMPLETE"
        },
        {
            "number": 18,
            "value": 21.278821333333333,
            "params": {
                "reset_peak": false,
                "rsi_min_thresh": 37,
                "rsi_max_thresh": 48,
                "adx_thresh": 54.46519206895665,
                "atr_mult": 11.839406192937043,
                "vwap_atr_mult": -0.7269563369646189,
                "buy_factor": 0.6589004733218364,
                "sell_factor": 0.045425459857480616,
                "trailstop_pct": 22.02508493292583,
                "sign_thresh_pair": "ema_3|ema_8"
            },
            "state": "COMPLETE"
        },
        {
            "number": 19,
            "value": 27.57071466666667,
            "params": {
                "reset_peak": false,
                "rsi_min_thresh": 31,
                "rsi_max_thresh": 56,
                "adx_thresh": 54.66967089366396,
                "atr_mult": 13.693479101008856,
                "vwap_atr_mult": -0.9721617545918524,
                "buy_factor": 0.6495340140133692,
                "sell_factor": 0.0703345114449482,
                "trailstop_pct": 13.240677913362088,
                "sign_thresh_pair": "ema_3|ema_8"
            },
            "state": "COMPLETE"
        },
        {
            "number": 20,
            "value": -8.813146666666691,
            "params": {
                "reset_peak": false,
                "rsi_min_thresh": 37,
                "rsi_max_thresh": 59,
                "adx_thresh": 57.769447351418734,
                "atr_mult": 10.16404437766609,
                "vwap_atr_mult": 0.4574721602651993,
                "buy_factor": 0.5638409055468274,
                "sell_factor": 0.013510980496242761,
                "trailstop_pct": 21.116201537635575,
                "sign_thresh_pair": "ema_3|ema_8"
            },
            "state": "COMPLETE"
        },
        {
            "number": 21,
            "value": 68.51577333333334,
            "params": {
                "reset_peak": false,
                "rsi_min_thresh": 43,
                "rsi_max_thresh": 54,
                "adx_thresh": 55.74242794960278,
                "atr_mult": 16.80782534419313,
                "vwap_atr_mult": -0.353467314463467,
                "buy_factor": 0.7284615335106608,
                "sell_factor": 0.04456512659454727,
                "trailstop_pct": 27.73901635168462,
                "sign_thresh_pair": "ema_3|ema_8"
            },
            "state": "COMPLETE"
        },
        {
            "number": 22,
            "value": 74.55066933333335,
            "params": {
                "reset_peak": false,
                "rsi_min_thresh": 43,
                "rsi_max_thresh": 51,
                "adx_thresh": 55.4119599867491,
                "atr_mult": 16.651050472987453,
                "vwap_atr_mult": -0.43894544122966184,
                "buy_factor": 0.7352781969153939,
                "sell_factor": 0.04714668193408586,
                "trailstop_pct": 27.496086053419027,
                "sign_thresh_pair": "ema_3|ema_8"
            },
            "state": "COMPLETE"
        },
        {
            "number": 23,
            "value": 64.50623466666667,
            "params": {
                "reset_peak": false,
                "rsi_min_thresh": 43,
                "rsi_max_thresh": 51,
                "adx_thresh": 56.48829583843444,
                "atr_mult": 15.058894302107083,
                "vwap_atr_mult": -0.42007262710010007,
                "buy_factor": 0.74011544077903,
                "sell_factor": 0.04778574070370866,
                "trailstop_pct": 26.28835459736098,
                "sign_thresh_pair": "ema_3|ema_8"
            },
            "state": "COMPLETE"
        },
        {
            "number": 24,
            "value": 22.15694133333335,
            "params": {
                "reset_peak": false,
                "rsi_min_thresh": 43,
                "rsi_max_thresh": 47,
                "adx_thresh": 58.31565266297935,
                "atr_mult": 16.651942501442445,
                "vwap_atr_mult": 0.21079600290524336,
                "buy_factor": 0.7940276503593517,
                "sell_factor": 0.02764780075067372,
                "trailstop_pct": 27.74150930114208,
                "sign_thresh_pair": "ema_3|ema_8"
            },
            "state": "COMPLETE"
        },
        {
            "number": 25,
            "value": 76.51813066666666,
            "params": {
                "reset_peak": false,
                "rsi_min_thresh": 39,
                "rsi_max_thresh": 51,
                "adx_thresh": 55.358429747490206,
                "atr_mult": 16.846710863208173,
                "vwap_atr_mult": -0.3390606537276092,
                "buy_factor": 0.7623841345153038,
                "sell_factor": 0.0705697503586789,
                "trailstop_pct": 27.93708666107371,
                "sign_thresh_pair": "ema_3|ema_8"
            },
            "state": "COMPLETE"
        },
        {
            "number": 26,
            "value": 60.43198400000001,
            "params": {
                "reset_peak": false,
                "rsi_min_thresh": 39,
                "rsi_max_thresh": 50,
                "adx_thresh": 53.78862242044478,
                "atr_mult": 16.792394914046916,
                "vwap_atr_mult": 0.71430820200472,
                "buy_factor": 0.7701933038776221,
                "sell_factor": 0.06832286583824548,
                "trailstop_pct": 25.15250211221854,
                "sign_thresh_pair": "ema_3|ema_8"
            },
            "state": "COMPLETE"
        },
        {
            "number": 27,
            "value": 40.11589599999999,
            "params": {
                "reset_peak": false,
                "rsi_min_thresh": 39,
                "rsi_max_thresh": 46,
                "adx_thresh": 56.448345250396095,
                "atr_mult": 15.101883965981479,
                "vwap_atr_mult": -0.5295270130053626,
                "buy_factor": 0.6902171018353256,
                "sell_factor": 0.07803350276511767,
                "trailstop_pct": 28.44845352772823,
                "sign_thresh_pair": "ema_3|ema_8"
            },
            "state": "COMPLETE"
        },
        {
            "number": 28,
            "value": 50.293458666666666,
            "params": {
                "reset_peak": false,
                "rsi_min_thresh": 44,
                "rsi_max_thresh": 51,
                "adx_thresh": 55.29532709867148,
                "atr_mult": 13.679566961885476,
                "vwap_atr_mult": -0.11013419905785171,
                "buy_factor": 0.7721352828378646,
                "sell_factor": 0.06478810394092652,
                "trailstop_pct": 23.541544918043215,
                "sign_thresh_pair": "ema_3|ema_8"
            },
            "state": "COMPLETE"
        },
        {
            "number": 29,
            "value": 39.152242666666666,
            "params": {
                "reset_peak": false,
                "rsi_min_thresh": 40,
                "rsi_max_thresh": 48,
                "adx_thresh": 52.11361268365928,
                "atr_mult": 16.069013097079978,
                "vwap_atr_mult": 0.19035018833288322,
                "buy_factor": 0.6190922589837172,
                "sell_factor": 0.07860552350118202,
                "trailstop_pct": 26.84886322570998,
                "sign_thresh_pair": "ema_3|ema_8"
            },
            "state": "COMPLETE"
        },
        {
            "number": 30,
            "value": 76.72018933333332,
            "params": {
                "reset_peak": false,
                "rsi_min_thresh": 39,
                "rsi_max_thresh": 52,
                "adx_thresh": 56.38831348072865,
                "atr_mult": 17.055126476782277,
                "vwap_atr_mult": 1.0783909752480998,
                "buy_factor": 0.7167350572013629,
                "sell_factor": 0.05058379182308676,
                "trailstop_pct": 28.807717971360383,
                "sign_thresh_pair": "ema_3|ema_8"
            },
            "state": "COMPLETE"
        },
        {
            "number": 31,
            "value": 71.08026133333335,
            "params": {
                "reset_peak": false,
                "rsi_min_thresh": 39,
                "rsi_max_thresh": 52,
                "adx_thresh": 55.150664175627526,
                "atr_mult": 17.003107965269653,
                "vwap_atr_mult": 0.8740918652715554,
                "buy_factor": 0.7209678448293805,
                "sell_factor": 0.04898147344943237,
                "trailstop_pct": 28.477663082734967,
                "sign_thresh_pair": "ema_3|ema_8"
            },
            "state": "COMPLETE"
        },
        {
            "number": 32,
            "value": 64.27615733333332,
            "params": {
                "reset_peak": false,
                "rsi_min_thresh": 38,
                "rsi_max_thresh": 51,
                "adx_thresh": 56.56486073270663,
                "atr_mult": 15.180075668132819,
                "vwap_atr_mult": 0.963756402830747,
                "buy_factor": 0.7245751077386493,
                "sell_factor": 0.05007413936481246,
                "trailstop_pct": 24.810192312372155,
                "sign_thresh_pair": "ema_3|ema_8"
            },
            "state": "COMPLETE"
        },
        {
            "number": 33,
            "value": 57.86351733333332,
            "params": {
                "reset_peak": false,
                "rsi_min_thresh": 41,
                "rsi_max_thresh": 49,
                "adx_thresh": 53.9125418407582,
                "atr_mult": 17.088398671345928,
                "vwap_atr_mult": 1.6565567602912394,
                "buy_factor": 0.7969017122960663,
                "sell_factor": 0.06391373288841214,
                "trailstop_pct": 28.345567841175427,
                "sign_thresh_pair": "ema_3|ema_8"
            },
            "state": "COMPLETE"
        },
        {
            "number": 34,
            "value": 60.152965333333334,
            "params": {
                "reset_peak": false,
                "rsi_min_thresh": 35,
                "rsi_max_thresh": 52,
                "adx_thresh": 55.04475486890475,
                "atr_mult": 16.730342256477783,
                "vwap_atr_mult": 2.4354089457649946,
                "buy_factor": 0.7455147566490837,
                "sell_factor": 0.05016657789109399,
                "trailstop_pct": 26.170437341931446,
                "sign_thresh_pair": "ema_3|ema_8"
            },
            "state": "COMPLETE"
        },
        {
            "number": 35,
            "value": 27.1318373333333,
            "params": {
                "reset_peak": false,
                "rsi_min_thresh": 39,
                "rsi_max_thresh": 55,
                "adx_thresh": 57.806848920397734,
                "atr_mult": 16.23977590963962,
                "vwap_atr_mult": 0.8627282117572483,
                "buy_factor": 0.7791096128910978,
                "sell_factor": 0.07906513100778151,
                "trailstop_pct": 29.0102561033126,
                "sign_thresh_pair": "ema_3|ema_8"
            },
            "state": "COMPLETE"
        },
        {
            "number": 36,
            "value": 46.02969866666663,
            "params": {
                "reset_peak": false,
                "rsi_min_thresh": 35,
                "rsi_max_thresh": 52,
                "adx_thresh": 56.83496724505853,
                "atr_mult": 15.760930399403748,
                "vwap_atr_mult": 1.188084723675611,
                "buy_factor": 0.4981046159103048,
                "sell_factor": 0.05199035046674021,
                "trailstop_pct": 27.263644904897486,
                "sign_thresh_pair": "ema_3|ema_8"
            },
            "state": "COMPLETE"
        },
        {
            "number": 37,
            "value": 65.40628000000001,
            "params": {
                "reset_peak": false,
                "rsi_min_thresh": 42,
                "rsi_max_thresh": 50,
                "adx_thresh": 56.200216074432056,
                "atr_mult": 16.357571452230474,
                "vwap_atr_mult": 1.5984256175087073,
                "buy_factor": 0.7096431274755683,
                "sell_factor": 0.06236177657703958,
                "trailstop_pct": 25.226165813462497,
                "sign_thresh_pair": "ema_3|ema_8"
            },
            "state": "COMPLETE"
        },
        {
            "number": 38,
            "value": 42.81415466666665,
            "params": {
                "reset_peak": false,
                "rsi_min_thresh": 36,
                "rsi_max_thresh": 54,
                "adx_thresh": 55.05081909707938,
                "atr_mult": 15.535277428374306,
                "vwap_atr_mult": 2.660715345960702,
                "buy_factor": 0.6781730945517245,
                "sell_factor": 0.0892599701546277,
                "trailstop_pct": 23.041210229203575,
                "sign_thresh_pair": "ema_3|ema_8"
            },
            "state": "COMPLETE"
        },
        {
            "number": 39,
            "value": 51.138920000000006,
            "params": {
                "reset_peak": false,
                "rsi_min_thresh": 41,
                "rsi_max_thresh": 49,
                "adx_thresh": 52.554434868882595,
                "atr_mult": 14.55539900943785,
                "vwap_atr_mult": 1.1616138553659512,
                "buy_factor": 0.750366461076739,
                "sell_factor": 0.039616123397400727,
                "trailstop_pct": 28.567005249833063,
                "sign_thresh_pair": "ema_3|ema_8"
            },
            "state": "COMPLETE"
        },
        {
            "number": 40,
            "value": 58.24305333333332,
            "params": {
                "reset_peak": false,
                "rsi_min_thresh": 42,
                "rsi_max_thresh": 52,
                "adx_thresh": 53.98047827863966,
                "atr_mult": 17.25720543238577,
                "vwap_atr_mult": -0.5910872519716023,
                "buy_factor": 0.6354271279332269,
                "sell_factor": 0.06138868983071617,
                "trailstop_pct": 23.72888988985799,
                "sign_thresh_pair": "ema_3|ema_8"
            },
            "state": "COMPLETE"
        },
        {
            "number": 41,
            "value": 72.22606933333334,
            "params": {
                "reset_peak": false,
                "rsi_min_thresh": 44,
                "rsi_max_thresh": 53,
                "adx_thresh": 55.42007073756986,
                "atr_mult": 17.57977358666948,
                "vwap_atr_mult": 0.3076419714989549,
                "buy_factor": 0.715610484496525,
                "sell_factor": 0.0534589737623267,
                "trailstop_pct": 29.924245602363605,
                "sign_thresh_pair": "ema_3|ema_8"
            },
            "state": "COMPLETE"
        },
        {
            "number": 42,
            "value": 31.076695999999966,
            "params": {
                "reset_peak": false,
                "rsi_min_thresh": 40,
                "rsi_max_thresh": 55,
                "adx_thresh": 57.44855879262695,
                "atr_mult": 16.374661011375892,
                "vwap_atr_mult": -0.24212945434409922,
                "buy_factor": 0.7175538050605657,
                "sell_factor": 0.053929727649777534,
                "trailstop_pct": 28.192927293545267,
                "sign_thresh_pair": "ema_3|ema_8"
            },
            "state": "COMPLETE"
        },
        {
            "number": 43,
            "value": 79.08347466666666,
            "params": {
                "reset_peak": false,
                "rsi_min_thresh": 38,
                "rsi_max_thresh": 51,
                "adx_thresh": 56.12394038627001,
                "atr_mult": 17.15944738183058,
                "vwap_atr_mult": 0.6872696620872301,
                "buy_factor": 0.6758011409497393,
                "sell_factor": 0.05876580221763241,
                "trailstop_pct": 15.158631289282436,
                "sign_thresh_pair": "ema_3|ema_8"
            },
            "state": "COMPLETE"
        },
        {
            "number": 44,
            "value": 76.37225866666665,
            "params": {
                "reset_peak": false,
                "rsi_min_thresh": 33,
                "rsi_max_thresh": 51,
                "adx_thresh": 56.13326287088545,
                "atr_mult": 17.494202124806964,
                "vwap_atr_mult": 0.6488533638130243,
                "buy_factor": 0.6722453806255455,
                "sell_factor": 0.05921933513320098,
                "trailstop_pct": 14.554304184583135,
                "sign_thresh_pair": "ema_3|ema_8"
            },
            "state": "COMPLETE"
        },
        {
            "number": 45,
            "value": 72.42010666666665,
            "params": {
                "reset_peak": false,
                "rsi_min_thresh": 33,
                "rsi_max_thresh": 48,
                "adx_thresh": 56.16453069341631,
                "atr_mult": 17.98137229014053,
                "vwap_atr_mult": 0.6962544505320031,
                "buy_factor": 0.6787899033098601,
                "sell_factor": 0.07049794890261517,
                "trailstop_pct": 15.058770173161644,
                "sign_thresh_pair": "ema_3|ema_8"
            },
            "state": "COMPLETE"
        },
        {
            "number": 46,
            "value": 40.65874933333334,
            "params": {
                "reset_peak": false,
                "rsi_min_thresh": 32,
                "rsi_max_thresh": 65,
                "adx_thresh": 56.936840925641384,
                "atr_mult": 16.35699787004197,
                "vwap_atr_mult": 1.3450752146618354,
                "buy_factor": 0.5956312474794148,
                "sell_factor": 0.05898878033565673,
                "trailstop_pct": 14.633934493723466,
                "sign_thresh_pair": "ema_3|ema_8"
            },
            "state": "COMPLETE"
        },
        {
            "number": 47,
            "value": 11.777069333333333,
            "params": {
                "reset_peak": false,
                "rsi_min_thresh": 36,
                "rsi_max_thresh": 51,
                "adx_thresh": 58.48202343679669,
                "atr_mult": 15.635542955541727,
                "vwap_atr_mult": 1.0853335330090124,
                "buy_factor": 0.6734468519424045,
                "sell_factor": 0.06645952214596151,
                "trailstop_pct": 10.07471036690727,
                "sign_thresh_pair": "ema_3|ema_8"
            },
            "state": "COMPLETE"
        },
        {
            "number": 48,
            "value": 58.38229866666666,
            "params": {
                "reset_peak": false,
                "rsi_min_thresh": 34,
                "rsi_max_thresh": 50,
                "adx_thresh": 55.99327340002206,
                "atr_mult": 17.412158764076672,
                "vwap_atr_mult": 0.5663802722295906,
                "buy_factor": 0.4157879089622804,
                "sell_factor": 0.07479264291890747,
                "trailstop_pct": 12.581230307450467,
                "sign_thresh_pair": "ema_3|ema_8"
            },
            "state": "COMPLETE"
        },
        {
            "number": 49,
            "value": 19.39019733333334,
            "params": {
                "reset_peak": false,
                "rsi_min_thresh": 30,
                "rsi_max_thresh": 46,
                "adx_thresh": 50.113355778073256,
                "atr_mult": 16.580386381590365,
                "vwap_atr_mult": 0.06604870796620155,
                "buy_factor": 0.7612108346873012,
                "sell_factor": 0.057949554378066086,
                "trailstop_pct": 17.021979606303024,
                "sign_thresh_pair": "ema_3|ema_8"
            },
            "state": "COMPLETE"
        },
        {
            "number": 50,
            "value": 17.828306666666656,
            "params": {
                "reset_peak": false,
                "rsi_min_thresh": 38,
                "rsi_max_thresh": 53,
                "adx_thresh": 57.6338879620709,
                "atr_mult": 15.394260733147817,
                "vwap_atr_mult": 1.445138335721481,
                "buy_factor": 0.7364622775347172,
                "sell_factor": 0.08401117565010123,
                "trailstop_pct": 15.540109812739052,
                "sign_thresh_pair": "ema_3|ema_8"
            },
            "state": "COMPLETE"
        },
        {
            "number": 51,
            "value": 69.37103733333333,
            "params": {
                "reset_peak": false,
                "rsi_min_thresh": 33,
                "rsi_max_thresh": 48,
                "adx_thresh": 56.36640925116606,
                "atr_mult": 17.95299237357698,
                "vwap_atr_mult": 0.7386227651306563,
                "buy_factor": 0.679093299042151,
                "sell_factor": 0.07306086274461651,
                "trailstop_pct": 14.622766569241398,
                "sign_thresh_pair": "ema_3|ema_8"
            },
            "state": "COMPLETE"
        },
        {
            "number": 52,
            "value": 66.78559200000001,
            "params": {
                "reset_peak": false,
                "rsi_min_thresh": 33,
                "rsi_max_thresh": 49,
                "adx_thresh": 54.74923090462914,
                "atr_mult": 17.396797627565807,
                "vwap_atr_mult": 0.6714272193294145,
                "buy_factor": 0.6379164256400137,
                "sell_factor": 0.060263603267661225,
                "trailstop_pct": 18.033541388742584,
                "sign_thresh_pair": "ema_3|ema_8"
            },
            "state": "COMPLETE"
        },
        {
            "number": 53,
            "value": 66.17458666666666,
            "params": {
                "reset_peak": false,
                "rsi_min_thresh": 32,
                "rsi_max_thresh": 47,
                "adx_thresh": 56.04352155738827,
                "atr_mult": 17.989720115992913,
                "vwap_atr_mult": 0.45649417062050923,
                "buy_factor": 0.6058303846900603,
                "sell_factor": 0.07066439508219378,
                "trailstop_pct": 12.774084705778284,
                "sign_thresh_pair": "ema_3|ema_8"
            },
            "state": "COMPLETE"
        },
        {
            "number": 54,
            "value": 53.57252266666665,
            "params": {
                "reset_peak": false,
                "rsi_min_thresh": 27,
                "rsi_max_thresh": 50,
                "adx_thresh": 57.21871655796888,
                "atr_mult": 15.930881088776182,
                "vwap_atr_mult": 1.7698677113731411,
                "buy_factor": 0.699829230717913,
                "sell_factor": 0.055590806169577046,
                "trailstop_pct": 15.830272257707366,
                "sign_thresh_pair": "ema_3|ema_8"
            },
            "state": "COMPLETE"
        },
        {
            "number": 55,
            "value": 52.336738666666655,
            "params": {
                "reset_peak": false,
                "rsi_min_thresh": 34,
                "rsi_max_thresh": 51,
                "adx_thresh": 55.627956237686085,
                "atr_mult": 16.96180311323289,
                "vwap_atr_mult": -0.7321744733237366,
                "buy_factor": 0.6667755403992988,
                "sell_factor": 0.06594269555209524,
                "trailstop_pct": 20.262192077150488,
                "sign_thresh_pair": "ema_3|ema_8"
            },
            "state": "COMPLETE"
        },
        {
            "number": 56,
            "value": 37.59346133333334,
            "params": {
                "reset_peak": false,
                "rsi_min_thresh": 35,
                "rsi_max_thresh": 47,
                "adx_thresh": 56.72872322444819,
                "atr_mult": 17.520147662078244,
                "vwap_atr_mult": 2.064363217302211,
                "buy_factor": 0.44482411704232916,
                "sell_factor": 0.07325653364762517,
                "trailstop_pct": 11.718882648929396,
                "sign_thresh_pair": "ema_3|ema_8"
            },
            "state": "COMPLETE"
        },
        {
            "number": 57,
            "value": 47.02272266666665,
            "params": {
                "reset_peak": false,
                "rsi_min_thresh": 36,
                "rsi_max_thresh": 49,
                "adx_thresh": 54.230577922850145,
                "atr_mult": 14.159269412229206,
                "vwap_atr_mult": 0.9823465364148497,
                "buy_factor": 0.6239860490658676,
                "sell_factor": 0.040885513242084094,
                "trailstop_pct": 14.430034750492355,
                "sign_thresh_pair": "ema_3|ema_8"
            },
            "state": "COMPLETE"
        },
        {
            "number": 58,
            "value": 52.35431999999999,
            "params": {
                "reset_peak": false,
                "rsi_min_thresh": 38,
                "rsi_max_thresh": 45,
                "adx_thresh": 55.95134215418891,
                "atr_mult": 17.025743382811882,
                "vwap_atr_mult": 0.8163524323790269,
                "buy_factor": 0.6490870508789013,
                "sell_factor": 0.0932806747070637,
                "trailstop_pct": 13.754396503459338,
                "sign_thresh_pair": "ema_3|ema_8"
            },
            "state": "COMPLETE"
        },
        {
            "number": 59,
            "value": 15.951135999999998,
            "params": {
                "reset_peak": false,
                "rsi_min_thresh": 31,
                "rsi_max_thresh": 53,
                "adx_thresh": 53.53955512458219,
                "atr_mult": 11.480465381182572,
                "vwap_atr_mult": -0.2108173608552681,
                "buy_factor": 0.7552795526375808,
                "sell_factor": 0.04645045684949971,
                "trailstop_pct": 16.372923152769893,
                "sign_thresh_pair": "ema_3|ema_8"
            },
            "state": "COMPLETE"
        },
        {
            "number": 60,
            "value": 39.02158666666666,
            "params": {
                "reset_peak": false,
                "rsi_min_thresh": 32,
                "rsi_max_thresh": 54,
                "adx_thresh": 54.837655311857205,
                "atr_mult": 12.200865734561964,
                "vwap_atr_mult": 0.18257961297458158,
                "buy_factor": 0.6852501084296163,
                "sell_factor": 0.030001715456947856,
                "trailstop_pct": 18.407901262807428,
                "sign_thresh_pair": "ema_3|ema_8"
            },
            "state": "COMPLETE"
        },
        {
            "number": 61,
            "value": 67.07977866666667,
            "params": {
                "reset_peak": false,
                "rsi_min_thresh": 44,
                "rsi_max_thresh": 56,
                "adx_thresh": 55.45901259672314,
                "atr_mult": 17.69151020853669,
                "vwap_atr_mult": 0.3213300998258083,
                "buy_factor": 0.7090683485692808,
                "sell_factor": 0.05594400843719323,
                "trailstop_pct": 29.247902527335178,
                "sign_thresh_pair": "ema_3|ema_8"
            },
            "state": "COMPLETE"
        },
        {
            "number": 62,
            "value": 83.358664,
            "params": {
                "reset_peak": false,
                "rsi_min_thresh": 44,
                "rsi_max_thresh": 52,
                "adx_thresh": 55.386866031504375,
                "atr_mult": 17.596868735705208,
                "vwap_atr_mult": 0.49456473076988483,
                "buy_factor": 0.7344270589404928,
                "sell_factor": 0.05240649771242039,
                "trailstop_pct": 15.415093279267127,
                "sign_thresh_pair": "ema_3|ema_8"
            },
            "state": "COMPLETE"
        },
        {
            "number": 63,
            "value": 78.33292266666668,
            "params": {
                "reset_peak": false,
                "rsi_min_thresh": 42,
                "rsi_max_thresh": 52,
                "adx_thresh": 56.223391583480854,
                "atr_mult": 17.256532564919357,
                "vwap_atr_mult": 0.49582196083915575,
                "buy_factor": 0.7768058135734854,
                "sell_factor": 0.051401111705378026,
                "trailstop_pct": 16.883677018387946,
                "sign_thresh_pair": "ema_3|ema_8"
            },
            "state": "COMPLETE"
        },
        {
            "number": 64,
            "value": 83.11575466666667,
            "params": {
                "reset_peak": false,
                "rsi_min_thresh": 42,
                "rsi_max_thresh": 51,
                "adx_thresh": 55.55168128130511,
                "atr_mult": 16.52550444981515,
                "vwap_atr_mult": 0.44274300016013735,
                "buy_factor": 0.7865889892735688,
                "sell_factor": 0.0428465467583624,
                "trailstop_pct": 17.178577708336988,
                "sign_thresh_pair": "ema_3|ema_8"
            },
            "state": "COMPLETE"
        },
        {
            "number": 65,
            "value": 72.813144,
            "params": {
                "reset_peak": false,
                "rsi_min_thresh": 42,
                "rsi_max_thresh": 52,
                "adx_thresh": 55.74852721388503,
                "atr_mult": 17.24201088162622,
                "vwap_atr_mult": 0.5354593886564023,
                "buy_factor": 0.7836187402741278,
                "sell_factor": 0.0367961021198897,
                "trailstop_pct": 17.483184730491775,
                "sign_thresh_pair": "ema_3|ema_8"
            },
            "state": "COMPLETE"
        },
        {
            "number": 66,
            "value": 58.9194,
            "params": {
                "reset_peak": false,
                "rsi_min_thresh": 41,
                "rsi_max_thresh": 53,
                "adx_thresh": 54.24950933087648,
                "atr_mult": 16.051741544342754,
                "vwap_atr_mult": 0.387813566797406,
                "buy_factor": 0.7866382555638157,
                "sell_factor": 0.04401115148034688,
                "trailstop_pct": 19.406003072071123,
                "sign_thresh_pair": "ema_3|ema_8"
            },
            "state": "COMPLETE"
        },
        {
            "number": 67,
            "value": 64.14498133333332,
            "params": {
                "reset_peak": false,
                "rsi_min_thresh": 40,
                "rsi_max_thresh": 52,
                "adx_thresh": 57.03043552795478,
                "atr_mult": 16.602912885114982,
                "vwap_atr_mult": 0.5532440406964305,
                "buy_factor": 0.7702681591002638,
                "sell_factor": 0.051672194090021356,
                "trailstop_pct": 16.211003914371574,
                "sign_thresh_pair": "ema_3|ema_8"
            },
            "state": "COMPLETE"
        },
        {
            "number": 68,
            "value": 36.17377333333331,
            "params": {
                "reset_peak": false,
                "rsi_min_thresh": 44,
                "rsi_max_thresh": 54,
                "adx_thresh": 56.65084290066803,
                "atr_mult": 10.82371400645905,
                "vwap_atr_mult": 1.0798539120273885,
                "buy_factor": 0.799006629132608,
                "sell_factor": 0.04215978288617543,
                "trailstop_pct": 17.106439464600633,
                "sign_thresh_pair": "ema_3|ema_8"
            },
            "state": "COMPLETE"
        },
        {
            "number": 69,
            "value": 49.27158399999998,
            "params": {
                "reset_peak": false,
                "rsi_min_thresh": 38,
                "rsi_max_thresh": 50,
                "adx_thresh": 56.41588801681554,
                "atr_mult": 13.085034075562074,
                "vwap_atr_mult": 0.05781887253200668,
                "buy_factor": 0.7567277132677536,
                "sell_factor": 0.05826851206021,
                "trailstop_pct": 13.91471403016376,
                "sign_thresh_pair": "ema_3|ema_8"
            },
            "state": "COMPLETE"
        },
        {
            "number": 70,
            "value": 78.15516266666664,
            "params": {
                "reset_peak": false,
                "rsi_min_thresh": 42,
                "rsi_max_thresh": 51,
                "adx_thresh": 55.197249931435245,
                "atr_mult": 17.063943065519194,
                "vwap_atr_mult": 0.9236169340395624,
                "buy_factor": 0.7314923200723552,
                "sell_factor": 0.04779193512028871,
                "trailstop_pct": 15.333089558514832,
                "sign_thresh_pair": "ema_3|ema_8"
            },
            "state": "COMPLETE"
        },
        {
            "number": 71,
            "value": 82.07123466666665,
            "params": {
                "reset_peak": false,
                "rsi_min_thresh": 42,
                "rsi_max_thresh": 51,
                "adx_thresh": 55.22087918456996,
                "atr_mult": 16.94904585906726,
                "vwap_atr_mult": 0.8356124079332021,
                "buy_factor": 0.7351227264276013,
                "sell_factor": 0.04832619298231759,
                "trailstop_pct": 15.462867540277724,
                "sign_thresh_pair": "ema_3|ema_8"
            },
            "state": "COMPLETE"
        },
        {
            "number": 72,
            "value": 86.50608533333335,
            "params": {
                "reset_peak": false,
                "rsi_min_thresh": 42,
                "rsi_max_thresh": 50,
                "adx_thresh": 55.17763139479644,
                "atr_mult": 16.91314529757019,
                "vwap_atr_mult": 0.8182350554612376,
                "buy_factor": 0.7325169674968726,
                "sell_factor": 0.03885118836617338,
                "trailstop_pct": 15.56520771756272,
                "sign_thresh_pair": "ema_3|ema_8"
            },
            "state": "COMPLETE"
        },
        {
            "number": 73,
            "value": 90.56564799999998,
            "params": {
                "reset_peak": false,
                "rsi_min_thresh": 43,
                "rsi_max_thresh": 50,
                "adx_thresh": 54.53836982324864,
                "atr_mult": 17.19124436281302,
                "vwap_atr_mult": 0.8557727003515059,
                "buy_factor": 0.7340902622768063,
                "sell_factor": 0.037656920188872296,
                "trailstop_pct": 15.511181451431836,
                "sign_thresh_pair": "ema_3|ema_8"
            },
            "state": "COMPLETE"
        }
    ]
}